{"zf7n6L1MrP/m+vQGOGlC8g==":"sticker-20171019105630-520x520.png","Nkku/bPwXbddNtDtFe4d5Q==":"mbr-720x1080.jpg","PAZ9tJ1gqtLMoWBzaJn8JQ==":"img-20170304-wa0006-640x480.jpg","KmDoo7Yykmmti2+SqMfTIA==":"619iecnbu+l._sl1018_-1018x679.jpg","eJUbSbnzCj5voh1W0H7ONw==":"mbr-1620x1080.jpg","5wjfUHl/ewFylXid5OqlEw==":"img-20171015-wa0037-640x640.jpg","bWSM0WkSBjMKuAO1hDwNmw==":"img-20171015-wa0004-1280x720.jpg","dYeojBYWSqIUX9ORa0+/ig==":"img-20170304-wa0008-1040x780.jpg","QOxlp0zojLFGpYyzkjfr2Q==":"img-20170304-wa0006-1-640x480.jpg","p5J0Jkp5e5tpsZxv94nH4w==":"img-20170930-wa0009-1280x853.jpg","U2QQW1ehEDmt1yABQ7aXbA==":"img-20170930-wa0008-1280x853.jpg","ziFwXxSFp90sHK2bLwG0aw==":"img-20171015-wa0032-1280x720.jpg","SLWQCJEpC1es7Z68JZfwfA==":"dsc-402-2000x1125.jpg","FLXjRnhl1gaug8xSh2afcg==":"dsc-395-2000x1125.jpg","wbKKytbvH7epoDWoujKy1w==":"img-20170913-wa0001-2000x1125.jpg","R/PHEpvlFYY04GCbSn6Shg==":"img-20170911-wa0013-1280x720.jpg","gXbZPakntlScPT39eQ/94Q==":"img-20170911-wa0014-1280x720.jpg","H6lO2xkB/xQXIuBjGciYWw==":"img-20170911-wa0015-1280x720.jpg","ZlQR8XahUEFi6xALfnPqFA==":"img-20170918-wa0006-905x1280.jpg","aPHzucJXbi9ybrJ+XT+GCA==":"img-20170913-wa0001-2000x1125-800x450.jpg","tTlFNtVkuhfU+2WYGWST9w==":"dsc-402-2000x1125-800x450.jpg","MG/yu8G4Ltv5MzyFsDoZ+g==":"img-20170930-wa0009-1280x853-800x533.jpg","pRb8w/mf+PsYZsWOlGd64w==":"img-20170304-wa0006-1-640x480-640x480.jpg","iPQsxH0VeIYUHwdiN2DzYg==":"dsc-11-2000x1125.jpg","lrU2YwxsZA+vNhd6XZB20w==":"img-20161223-wa0014-452x503.jpg","ex5/I+JXfVRhZpkLANPeBg==":"img-20171015-wa0004-1-1280x720.jpg"}